django_pageblocks-2.0.0.dist-info/DESCRIPTION.rst
django_pageblocks-2.0.0.dist-info/METADATA
django_pageblocks-2.0.0.dist-info/RECORD
django_pageblocks-2.0.0.dist-info/WHEEL
django_pageblocks-2.0.0.dist-info/metadata.json
django_pageblocks-2.0.0.dist-info/top_level.txt
pageblocks/__init__.py
pageblocks/exportimport.py
pageblocks/forms.py
pageblocks/models.py
pageblocks/urls.py
pageblocks/migrations/0001_initial.py
pageblocks/migrations/0002_simpleimageblock.py
pageblocks/migrations/0003_auto_20161125_1441.py
pageblocks/migrations/__init__.py
pageblocks/templates/__init__.py
pageblocks/templates/pageblocks/__init__.py
pageblocks/templates/pageblocks/htmlblock.html
pageblocks/templates/pageblocks/htmlblock_wysiwyg.html
pageblocks/templates/pageblocks/imageblock.html
pageblocks/templates/pageblocks/imageblock_summary.html
pageblocks/templates/pageblocks/imagepullquoteblock.html
pageblocks/templates/pageblocks/imagepullquoteblock_summary.html
pageblocks/templates/pageblocks/pullquoteblock.html
pageblocks/templates/pageblocks/simpleimageblock.html
pageblocks/templates/pageblocks/textblock.html
pageblocks/tests/__init__.py
pageblocks/tests/factories.py
pageblocks/tests/test_models.py
