Metadata-Version: 2.0
Name: django-pageblocks
Version: 2.0.0
Summary: Basic Pageblocks to go along with django-pagetree
Home-page: https://github.com/ccnmtl/django-pageblocks
Author: Anders Pearson
Author-email: anders@columbia.edu
License: BSD
Platform: any
Requires-Dist: django-pagetree (>=1.1.0)
